{"frames":[{"frame":{"x":32,"y":43,"w":16,"h":14}},{"frame":{"x":48,"y":43,"w":16,"h":14}},{"frame":{"x":15,"y":153,"w":16,"h":16}},{"frame":{"x":0,"y":137,"w":16,"h":16}},{"frame":{"x":112,"y":121,"w":16,"h":16}},{"frame":{"x":80,"y":121,"w":16,"h":16}},{"frame":{"x":96,"y":121,"w":16,"h":16}},{"frame":{"x":48,"y":121,"w":16,"h":16}},{"frame":{"x":0,"y":43,"w":16,"h":14}},{"frame":{"x":80,"y":43,"w":16,"h":14}},{"frame":{"x":106,"y":208,"w":16,"h":24}},{"frame":{"x":82,"y":208,"w":8,"h":24}},{"frame":{"x":90,"y":208,"w":8,"h":24}},{"frame":{"x":66,"y":208,"w":16,"h":24}},{"frame":{"x":50,"y":208,"w":8,"h":24}},{"frame":{"x":98,"y":208,"w":8,"h":24}},{"frame":{"x":0,"y":232,"w":16,"h":24}},{"frame":{"x":40,"y":232,"w":8,"h":24}},{"frame":{"x":16,"y":232,"w":8,"h":24}},{"frame":{"x":24,"y":232,"w":16,"h":24}},{"frame":{"x":58,"y":208,"w":8,"h":24}},{"frame":{"x":42,"y":208,"w":8,"h":24}},{"frame":{"x":16,"y":0,"w":7,"h":7}},{"frame":{"x":16,"y":185,"w":24,"h":19}},{"frame":{"x":16,"y":137,"w":24,"h":16}},{"frame":{"x":40,"y":185,"w":24,"h":19}},{"frame":{"x":40,"y":137,"w":24,"h":16}},{"frame":{"x":88,"y":185,"w":24,"h":19}},{"frame":{"x":80,"y":137,"w":24,"h":16}},{"frame":{"x":64,"y":185,"w":24,"h":19}},{"frame":{"x":104,"y":137,"w":24,"h":16}},{"frame":{"x":62,"y":0,"w":16,"h":8}},{"frame":{"x":78,"y":0,"w":16,"h":8}},{"frame":{"x":94,"y":0,"w":16,"h":8}},{"frame":{"x":23,"y":8,"w":16,"h":8}},{"frame":{"x":0,"y":8,"w":16,"h":8}},{"frame":{"x":23,"y":0,"w":16,"h":8}},{"frame":{"x":0,"y":153,"w":15,"h":16}},{"frame":{"x":64,"y":137,"w":16,"h":16}},{"frame":{"x":16,"y":121,"w":16,"h":16}},{"frame":{"x":44,"y":16,"w":16,"h":12}},{"frame":{"x":39,"y":8,"w":16,"h":8}},{"frame":{"x":32,"y":121,"w":16,"h":16}},{"frame":{"x":20,"y":16,"w":16,"h":12}},{"frame":{"x":55,"y":8,"w":16,"h":8}},{"frame":{"x":64,"y":121,"w":16,"h":16}},{"frame":{"x":60,"y":16,"w":16,"h":12}},{"frame":{"x":79,"y":8,"w":16,"h":8}},{"frame":{"x":64,"y":43,"w":16,"h":14}},{"frame":{"x":96,"y":43,"w":16,"h":14}},{"frame":{"x":16,"y":43,"w":16,"h":14}},{"frame":{"x":108,"y":29,"w":16,"h":14}},{"frame":{"x":40,"y":588,"w":40,"h":40}},{"frame":{"x":30,"y":169,"w":16,"h":16}},{"frame":{"x":0,"y":89,"w":16,"h":16}},{"frame":{"x":108,"y":57,"w":16,"h":16}},{"frame":{"x":80,"y":89,"w":16,"h":16}},{"frame":{"x":0,"y":105,"w":16,"h":16}},{"frame":{"x":96,"y":89,"w":16,"h":16}},{"frame":{"x":112,"y":89,"w":16,"h":16}},{"frame":{"x":64,"y":105,"w":16,"h":16}},{"frame":{"x":24,"y":29,"w":12,"h":13}},{"frame":{"x":108,"y":16,"w":12,"h":13}},{"frame":{"x":0,"y":29,"w":12,"h":13}},{"frame":{"x":96,"y":16,"w":12,"h":13}},{"frame":{"x":79,"y":153,"w":14,"h":16}},{"frame":{"x":0,"y":169,"w":14,"h":16}},{"frame":{"x":93,"y":153,"w":14,"h":16}},{"frame":{"x":94,"y":169,"w":14,"h":16}},{"frame":{"x":108,"y":169,"w":16,"h":16}},{"frame":{"x":62,"y":169,"w":16,"h":16}},{"frame":{"x":47,"y":153,"w":16,"h":16}},{"frame":{"x":46,"y":169,"w":16,"h":16}},{"frame":{"x":0,"y":185,"w":16,"h":16}},{"frame":{"x":14,"y":169,"w":16,"h":16}},{"frame":{"x":107,"y":153,"w":16,"h":16}},{"frame":{"x":63,"y":153,"w":16,"h":16}},{"frame":{"x":78,"y":169,"w":16,"h":16}},{"frame":{"x":31,"y":153,"w":16,"h":16}},{"frame":{"x":48,"y":89,"w":16,"h":16}},{"frame":{"x":64,"y":73,"w":16,"h":16}},{"frame":{"x":48,"y":73,"w":16,"h":16}},{"frame":{"x":96,"y":73,"w":16,"h":16}},{"frame":{"x":16,"y":89,"w":16,"h":16}},{"frame":{"x":112,"y":73,"w":16,"h":16}},{"frame":{"x":80,"y":73,"w":16,"h":16}},{"frame":{"x":16,"y":73,"w":16,"h":16}},{"frame":{"x":76,"y":57,"w":16,"h":16}},{"frame":{"x":92,"y":57,"w":16,"h":16}},{"frame":{"x":32,"y":73,"w":16,"h":16}},{"frame":{"x":0,"y":73,"w":16,"h":16}},{"frame":{"x":0,"y":121,"w":16,"h":16}},{"frame":{"x":71,"y":8,"w":8,"h":8}},{"frame":{"x":95,"y":8,"w":8,"h":8}},{"frame":{"x":96,"y":105,"w":16,"h":16}},{"frame":{"x":76,"y":16,"w":8,"h":12}},{"frame":{"x":36,"y":16,"w":8,"h":12}},{"frame":{"x":62,"y":548,"w":40,"h":40}},{"frame":{"x":22,"y":548,"w":40,"h":40}},{"frame":{"x":0,"y":588,"w":40,"h":40}},{"frame":{"x":0,"y":668,"w":40,"h":40}},{"frame":{"x":40,"y":628,"w":40,"h":40}},{"frame":{"x":80,"y":628,"w":40,"h":40}},{"frame":{"x":0,"y":628,"w":40,"h":40}},{"frame":{"x":80,"y":588,"w":40,"h":40}},{"frame":{"x":103,"y":258,"w":16,"h":32}},{"frame":{"x":56,"y":258,"w":16,"h":32}},{"frame":{"x":96,"y":290,"w":16,"h":32}},{"frame":{"x":24,"y":258,"w":16,"h":32}},{"frame":{"x":48,"y":510,"w":24,"h":38}},{"frame":{"x":48,"y":472,"w":16,"h":38}},{"frame":{"x":48,"y":358,"w":18,"h":38}},{"frame":{"x":28,"y":358,"w":20,"h":38}},{"frame":{"x":0,"y":358,"w":28,"h":38}},{"frame":{"x":96,"y":232,"w":24,"h":26}},{"frame":{"x":28,"y":208,"w":14,"h":23}},{"frame":{"x":57,"y":57,"w":19,"h":15}},{"frame":{"x":14,"y":208,"w":14,"h":23}},{"frame":{"x":38,"y":57,"w":19,"h":15}},{"frame":{"x":12,"y":29,"w":12,"h":13}},{"frame":{"x":84,"y":16,"w":12,"h":13}},{"frame":{"x":36,"y":29,"w":12,"h":13}},{"frame":{"x":48,"y":29,"w":12,"h":13}},{"frame":{"x":26,"y":434,"w":20,"h":38}},{"frame":{"x":90,"y":358,"w":22,"h":38}},{"frame":{"x":62,"y":434,"w":22,"h":38}},{"frame":{"x":100,"y":434,"w":28,"h":38}},{"frame":{"x":0,"y":258,"w":24,"h":26}},{"frame":{"x":84,"y":434,"w":16,"h":38}},{"frame":{"x":46,"y":434,"w":16,"h":38}},{"frame":{"x":0,"y":472,"w":20,"h":38}},{"frame":{"x":0,"y":396,"w":26,"h":38}},{"frame":{"x":44,"y":396,"w":24,"h":38}},{"frame":{"x":103,"y":322,"w":24,"h":36}},{"frame":{"x":63,"y":322,"w":16,"h":32}},{"frame":{"x":16,"y":322,"w":16,"h":32}},{"frame":{"x":112,"y":290,"w":16,"h":32}},{"frame":{"x":0,"y":322,"w":16,"h":32}},{"frame":{"x":84,"y":396,"w":24,"h":38}},{"frame":{"x":68,"y":396,"w":16,"h":38}},{"frame":{"x":26,"y":396,"w":18,"h":38}},{"frame":{"x":0,"y":510,"w":20,"h":38}},{"frame":{"x":20,"y":510,"w":28,"h":38}},{"frame":{"x":48,"y":232,"w":24,"h":26}},{"frame":{"x":112,"y":185,"w":14,"h":23}},{"frame":{"x":19,"y":57,"w":19,"h":15}},{"frame":{"x":0,"y":208,"w":14,"h":23}},{"frame":{"x":0,"y":57,"w":19,"h":15}},{"frame":{"x":96,"y":29,"w":12,"h":13}},{"frame":{"x":84,"y":29,"w":12,"h":13}},{"frame":{"x":60,"y":29,"w":12,"h":13}},{"frame":{"x":72,"y":29,"w":12,"h":13}},{"frame":{"x":94,"y":510,"w":20,"h":38}},{"frame":{"x":0,"y":548,"w":22,"h":38}},{"frame":{"x":72,"y":510,"w":22,"h":38}},{"frame":{"x":20,"y":472,"w":28,"h":38}},{"frame":{"x":72,"y":232,"w":24,"h":26}},{"frame":{"x":64,"y":472,"w":16,"h":38}},{"frame":{"x":100,"y":472,"w":16,"h":38}},{"frame":{"x":80,"y":472,"w":20,"h":38}},{"frame":{"x":0,"y":434,"w":26,"h":38}},{"frame":{"x":66,"y":358,"w":24,"h":38}},{"frame":{"x":79,"y":322,"w":24,"h":36}},{"frame":{"x":4,"y":0,"w":4,"h":5}},{"frame":{"x":16,"y":8,"w":7,"h":8}},{"frame":{"x":0,"y":0,"w":4,"h":5}},{"frame":{"x":110,"y":0,"w":7,"h":8}},{"frame":{"x":54,"y":0,"w":8,"h":8}},{"frame":{"x":46,"y":0,"w":8,"h":8}},{"frame":{"x":10,"y":16,"w":10,"h":10}},{"frame":{"x":16,"y":105,"w":16,"h":16}},{"frame":{"x":32,"y":322,"w":31,"h":32}},{"frame":{"x":39,"y":0,"w":7,"h":8}},{"frame":{"x":12,"y":0,"w":4,"h":5}},{"frame":{"x":8,"y":0,"w":4,"h":5}},{"frame":{"x":111,"y":8,"w":7,"h":8}},{"frame":{"x":118,"y":8,"w":8,"h":8}},{"frame":{"x":103,"y":8,"w":8,"h":8}},{"frame":{"x":0,"y":16,"w":10,"h":10}},{"frame":{"x":48,"y":105,"w":16,"h":16}},{"frame":{"x":72,"y":258,"w":31,"h":32}},{"frame":{"x":40,"y":258,"w":16,"h":32}},{"frame":{"x":48,"y":290,"w":48,"h":32}},{"frame":{"x":80,"y":105,"w":16,"h":16}},{"frame":{"x":112,"y":105,"w":16,"h":16}},{"frame":{"x":32,"y":89,"w":16,"h":16}},{"frame":{"x":56,"y":668,"w":48,"h":80}},{"frame":{"x":48,"y":668,"w":8,"h":48}},{"frame":{"x":40,"y":668,"w":8,"h":48}},{"frame":{"x":0,"y":290,"w":24,"h":32}},{"frame":{"x":24,"y":290,"w":24,"h":32}},{"frame":{"x":32,"y":105,"w":16,"h":16}},{"frame":{"x":64,"y":89,"w":16,"h":16}}]}